odoo/addons/report_context/README.rst
odoo/addons/report_context/__init__.py
odoo/addons/report_context/__manifest__.py
odoo/addons/report_context/controllers/__init__.py
odoo/addons/report_context/controllers/main.py
odoo/addons/report_context/data/config_parameter.xml
odoo/addons/report_context/i18n/report_context.pot
odoo/addons/report_context/models/__init__.py
odoo/addons/report_context/models/ir_actions_report.py
odoo/addons/report_context/readme/CONTRIBUTORS.rst
odoo/addons/report_context/readme/DESCRIPTION.rst
odoo/addons/report_context/readme/USAGE.rst
odoo/addons/report_context/static/description/icon.png
odoo/addons/report_context/static/description/index.html
odoo/addons/report_context/tests/__init__.py
odoo/addons/report_context/tests/test_report_context.py
odoo/addons/report_context/views/ir_actions_report.xml
odoo11_addon_report_context-11.0.1.0.0.99.dev4.dist-info/METADATA
odoo11_addon_report_context-11.0.1.0.0.99.dev4.dist-info/WHEEL
odoo11_addon_report_context-11.0.1.0.0.99.dev4.dist-info/top_level.txt
odoo11_addon_report_context-11.0.1.0.0.99.dev4.dist-info/RECORD
